email_forwarding_checker/__init__.py
email_forwarding_checker/__main__.py
email_forwarding_checker/daemon.py
email_forwarding_checker/forwarding_checker.py
email_forwarding_checker/main.py
email_forwarding_checker/mqtt.py
email_forwarding_checker-0.5.0.dist-info/METADATA
email_forwarding_checker-0.5.0.dist-info/WHEEL
email_forwarding_checker-0.5.0.dist-info/entry_points.txt
email_forwarding_checker-0.5.0.dist-info/licenses/AUTHORS.rst
email_forwarding_checker-0.5.0.dist-info/licenses/LICENSE
email_forwarding_checker-0.5.0.dist-info/RECORD
