Metadata-Version: 2.4
Name: email-forwarding-checker
Version: 0.5.0
Summary: Checks if a configured email forwarding is working
License-File: AUTHORS.rst
License-File: LICENSE
Requires-Python: >=3.12
Requires-Dist: paho-mqtt==1.*
Requires-Dist: pyyaml==6.*
Requires-Dist: schedule==1.*
Provides-Extra: dev
Requires-Dist: types-paho-mqtt; extra == 'dev'
